apollo_py_core/__init__.py
apollo_py_core/robot_modules/__init__.py
apollo_py_core/robot_modules/chain_module.py
apollo_py_core/robot_modules/connections_module.py
apollo_py_core/robot_modules/dof_module.py
apollo_py_core/robot_modules/mesh_modules/__init__.py
apollo_py_core/robot_modules/mesh_modules/convex_decomposition_meshes_module.py
apollo_py_core/robot_modules/mesh_modules/convex_hull_meshes_module.py
apollo_py_core/robot_modules/mesh_modules/original_meshes_module.py
apollo_py_core/robot_modules/mesh_modules/plain_meshes_module.py
apollo_py_core/robot_modules/urdf_module.py
apollo_py_core/utils/__init__.py
apollo_py_core/utils/robot_preprocessor_directories.py
apollo_py_core-0.0.3.dist-info/LICENSE
apollo_py_core-0.0.3.dist-info/METADATA
apollo_py_core-0.0.3.dist-info/WHEEL
apollo_py_core-0.0.3.dist-info/RECORD
